aiohttp_socks/__init__.py
aiohttp_socks/_deprecated.py
aiohttp_socks/connector.py
aiohttp_socks/utils.py
aiohttp_socks-0.9.1.dist-info/LICENSE.txt
aiohttp_socks-0.9.1.dist-info/METADATA
aiohttp_socks-0.9.1.dist-info/WHEEL
aiohttp_socks-0.9.1.dist-info/top_level.txt
aiohttp_socks-0.9.1.dist-info/RECORD
