Metadata-Version: 2.1
Name: aiohttp_socks
Version: 0.9.1
Summary: Proxy connector for aiohttp
Author-email: Roman Snegirev <snegiryev@gmail.com>
License: Apache-2.0
Project-URL: homepage, https://github.com/romis2012/aiohttp-socks
Project-URL: repository, https://github.com/romis2012/aiohttp-socks
Keywords: asyncio,aiohttp,socks,socks5,socks4,http,proxy
Classifier: Development Status :: 4 - Beta
Classifier: Programming Language :: Python
Classifier: Programming Language :: Python :: 3
Classifier: Programming Language :: Python :: 3 :: Only
Classifier: Programming Language :: Python :: 3.8
Classifier: Programming Language :: Python :: 3.9
Classifier: Programming Language :: Python :: 3.10
Classifier: Programming Language :: Python :: 3.11
Classifier: Programming Language :: Python :: 3.12
Classifier: Programming Language :: Python :: 3.13
Classifier: Operating System :: MacOS
Classifier: Operating System :: Microsoft
Classifier: Operating System :: POSIX :: Linux
Classifier: Topic :: Internet :: WWW/HTTP
Classifier: Intended Audience :: Developers
Classifier: Framework :: AsyncIO
Classifier: License :: OSI Approved :: Apache Software License
Requires-Python: >=3.8.0
License-File: LICENSE.txt
Requires-Dist: aiohttp>=3.10.0
Requires-Dist: python-socks[asyncio]<3.0.0,>=2.4.3
